{
  "caaba": {
    "definitions": [],
    "examples": [],
    "synonyms": [
      "kaaba",
      "caaba"
    ]
  },
  "caber": {
    "definitions": [
      "colocar roupas no  corpo: , , ,,",
      "conformar com algum formato ou tamanho"
    ],
    "examples": [
      "O que devo vestir hoje?",
      "Ele usou seu melhor terno  no casamento",
      "A princesa usou um vestido  azul longo",
      "A rainha colocou as vestes imponentes",
      "Ele cabia no seus jeans"
    ],
    "synonyms": [
      "pôr",
      "usar",
      "trazer",
      "colocar",
      "caber",
      "vestir",
      "servir",
      "ficar"
    ]
  },
  "cabos": {
    "definitions": [],
    "examples": [],
    "synonyms": [
      "cabos",
      "cabo",
      "promontório",
      "cabeceiros"
    ]
  },
  "caboz": {
    "definitions": [],
    "examples": [],
    "synonyms": [
      "caboz",
      "gobiidae"
    ]
  },
  "cabra": {
    "definitions": [],
    "examples": [],
    "synonyms": [
      "bode",
      "cabrito",
      "cabra"
    ]
  },
  "cabul": {
    "definitions": [],
    "examples": [],
    "synonyms": [
      "cabul"
    ]
  },
  "cacau": {
    "definitions": [],
    "examples": [],
    "synonyms": [
      "pralina",
      "chocolate",
      "cacau",
      "cacaueiro"
    ]
  },
  "cache": {
    "definitions": [],
    "examples": [],
    "synonyms": [
      "cachê",
      "cache",
      "numerário",
      "dinheiro"
    ]
  },
  "cachi": {
    "definitions": [],
    "examples": [],
    "synonyms": [
      "cachi"
    ]
  },
  "cacho": {
    "definitions": [],
    "examples": [],
    "synonyms": [
      "anel",
      "cacho",
      "racemo"
    ]
  },
  "cachê": {
    "definitions": [],
    "examples": [],
    "synonyms": [
      "cachê",
      "cache"
    ]
  },
  "cacto": {
    "definitions": [],
    "examples": [],
    "synonyms": [
      "cactaceae",
      "cactus",
      "cacto"
    ]
  },
  "cadmo": {
    "definitions": [],
    "examples": [],
    "synonyms": [
      "cadmo"
    ]
  },
  "cafés": {
    "definitions": [],
    "examples": [],
    "synonyms": [
      "restaurante",
      "cafeteria",
      "café",
      "lanchonete",
      "cafés"
    ]
  },
  "cagar": {
    "definitions": [],
    "examples": [],
    "synonyms": [
      "cagar",
      "defecar"
    ]
  },
  "caiar": {
    "definitions": [
      "cobrir com cal"
    ],
    "examples": [
      "paredes de cal"
    ],
    "synonyms": [
      "caiar",
      "acobertar"
    ]
  },
  "cairo": {
    "definitions": [],
    "examples": [],
    "synonyms": [
      "cairo"
    ]
  },
  "caixa": {
    "definitions": [],
    "examples": [],
    "synonyms": [
      "caixa",
      "féretro",
      "caixão",
      "esquife",
      "ataúde",
      "carcaça",
      "gaveta",
      "vaso",
      "jarro",
      "vasilha",
      "continente",
      "contentor",
      "contentores",
      "contêiner",
      "multibanco",
      "bancário"
    ]
  },
  "cajun": {
    "definitions": [],
    "examples": [],
    "synonyms": [
      "cajun"
    ]
  },
  "calar": {
    "definitions": [],
    "examples": [],
    "synonyms": [
      "calar"
    ]
  },
  "calau": {
    "definitions": [],
    "examples": [],
    "synonyms": [
      "calau"
    ]
  },
  "calda": {
    "definitions": [
      "um líquido pegajoso doce espesso"
    ],
    "examples": [],
    "synonyms": [
      "calda",
      "xarope",
      "garrafada"
    ]
  },
  "caldo": {
    "definitions": [],
    "examples": [],
    "synonyms": [
      "caldo",
      "olha"
    ]
  },
  "calha": {
    "definitions": [],
    "examples": [],
    "synonyms": [
      "calha",
      "rego"
    ]
  },
  "calla": {
    "definitions": [],
    "examples": [],
    "synonyms": [
      "calla"
    ]
  },
  "calma": {
    "definitions": [],
    "examples": [],
    "synonyms": [
      "calma",
      "equanimidade",
      "tranquilidade",
      "sereno",
      "calmo",
      "tranquilo",
      "sossegado",
      "tranqüilo"
    ]
  },
  "calmo": {
    "definitions": [],
    "examples": [],
    "synonyms": [
      "sereno",
      "calmo",
      "tranquilo",
      "sossegado",
      "tranqüilo",
      "calma",
      "quieto"
    ]
  },
  "calor": {
    "definitions": [],
    "examples": [],
    "synonyms": [
      "calor",
      "febre",
      "temperatura"
    ]
  },
  "calvo": {
    "definitions": [],
    "examples": [],
    "synonyms": [
      "careca",
      "calvo"
    ]
  },
  "calão": {
    "definitions": [],
    "examples": [],
    "synonyms": [
      "gíria",
      "jargão",
      "calão"
    ]
  },
  "calça": {
    "definitions": [
      "roupa de baixo usada por mulheres"
    ],
    "examples": [],
    "synonyms": [
      "calça",
      "perna",
      "calcinha"
    ]
  },
  "camas": {
    "definitions": [],
    "examples": [],
    "synonyms": [
      "camas",
      "leito",
      "cama"
    ]
  },
  "campo": {
    "definitions": [
      "Instalação que consiste em uma área circunscrita de terra ou água preparada para um esporte."
    ],
    "examples": [],
    "synonyms": [
      "campo",
      "gramado",
      "terreno",
      "campos",
      "teatro",
      "pista",
      "domínio",
      "disciplina"
    ]
  },
  "canal": {
    "definitions": [],
    "examples": [],
    "synonyms": [
      "canal",
      "duto",
      "ducto",
      "pipeline",
      "condutas",
      "canais",
      "conduto",
      "cano",
      "tubo",
      "cachimbo",
      "hidrovia",
      "hidrovias",
      "tubulação",
      "aqueduto",
      "canaleta"
    ]
  },
  "canaã": {
    "definitions": [],
    "examples": [],
    "synonyms": [
      "canaã"
    ]
  },
  "canga": {
    "definitions": [],
    "examples": [],
    "synonyms": [
      "canga",
      "jugo"
    ]
  },
  "canil": {
    "definitions": [],
    "examples": [],
    "synonyms": [
      "canil",
      "casota"
    ]
  },
  "canis": {
    "definitions": [],
    "examples": [],
    "synonyms": [
      "canis"
    ]
  },
  "canja": {
    "definitions": [],
    "examples": [],
    "synonyms": [
      "canja"
    ]
  },
  "canoa": {
    "definitions": [],
    "examples": [],
    "synonyms": [
      "canoa"
    ]
  },
  "canto": {
    "definitions": [],
    "examples": [],
    "synonyms": [
      "canto",
      "canção",
      "quina",
      "recanto",
      "rincão",
      "vértice"
    ]
  },
  "capar": {
    "definitions": [
      "remover os testículos de um animal do sexo masculino",
      "remover os testículos de um animal macho"
    ],
    "examples": [],
    "synonyms": [
      "capar",
      "castrar",
      "emascular"
    ]
  },
  "capaz": {
    "definitions": [],
    "examples": [],
    "synonyms": [
      "capaz",
      "adequado",
      "apropriado",
      "desejável",
      "conveniente",
      "correspondente",
      "apto",
      "inventivo",
      "engenhoso",
      "habilidoso",
      "desenvolto"
    ]
  },
  "capex": {
    "definitions": [],
    "examples": [],
    "synonyms": [
      "capex"
    ]
  },
  "capra": {
    "definitions": [],
    "examples": [],
    "synonyms": [
      "capra"
    ]
  },
  "capri": {
    "definitions": [],
    "examples": [],
    "synonyms": [
      "capri"
    ]
  },
  "capuz": {
    "definitions": [],
    "examples": [],
    "synonyms": [
      "capucha",
      "capuz",
      "coberta",
      "capô"
    ]
  },
  "capão": {
    "definitions": [
      "frango macho castrado"
    ],
    "examples": [],
    "synonyms": [
      "castrado",
      "capão"
    ]
  },
  "caqui": {
    "definitions": [],
    "examples": [],
    "synonyms": [
      "caqui",
      "diospireiro",
      "caquizeiro",
      "dióspiro"
    ]
  },
  "carda": {
    "definitions": [],
    "examples": [],
    "synonyms": [
      "carda"
    ]
  },
  "cardo": {
    "definitions": [],
    "examples": [],
    "synonyms": [
      "cardo"
    ]
  },
  "carex": {
    "definitions": [],
    "examples": [],
    "synonyms": [
      "carex"
    ]
  },
  "carga": {
    "definitions": [],
    "examples": [],
    "synonyms": [
      "carga",
      "preocupação",
      "fardo"
    ]
  },
  "cargo": {
    "definitions": [
      "um trabalho em uma organização",
      "uma posição em uma organização"
    ],
    "examples": [],
    "synonyms": [
      "cargo",
      "ofício",
      "poder",
      "posição",
      "posto"
    ]
  },
  "caril": {
    "definitions": [],
    "examples": [],
    "synonyms": [
      "curry",
      "caril"
    ]
  },
  "carma": {
    "definitions": [],
    "examples": [],
    "synonyms": [
      "karma",
      "carma"
    ]
  },
  "carne": {
    "definitions": [],
    "examples": [],
    "synonyms": [
      "vianda",
      "carne",
      "polpa",
      "corpo",
      "anatomia",
      "bife"
    ]
  },
  "carpa": {
    "definitions": [],
    "examples": [],
    "synonyms": [
      "carpa"
    ]
  },
  "carpo": {
    "definitions": [],
    "examples": [],
    "synonyms": [
      "pulso",
      "carpo",
      "punho"
    ]
  },
  "carro": {
    "definitions": [],
    "examples": [],
    "synonyms": [
      "carro",
      "carroça",
      "trem",
      "vagão",
      "vagões",
      "automotora",
      "comboio",
      "automóvel",
      "auto",
      "veículo",
      "máquina",
      "viatura"
    ]
  },
  "carta": {
    "definitions": [],
    "examples": [],
    "synonyms": [
      "cartão",
      "carta",
      "placa",
      "baralho",
      "papel",
      "epístola",
      "missiva"
    ]
  },
  "carum": {
    "definitions": [],
    "examples": [],
    "synonyms": [
      "carum"
    ]
  },
  "carya": {
    "definitions": [],
    "examples": [],
    "synonyms": [
      "carya"
    ]
  },
  "casal": {
    "definitions": [],
    "examples": [],
    "synonyms": [
      "matrimônio",
      "matrimónio",
      "conúbio",
      "casamento",
      "casal",
      "dupla"
    ]
  },
  "casar": {
    "definitions": [
      "fazer dois objetos, idéias ou pessoas ficarem juntos",
      "tomar em casamento"
    ],
    "examples": [],
    "synonyms": [
      "casar",
      "acoplar",
      "emparelhar",
      "juntar",
      "esposar"
    ]
  },
  "casca": {
    "definitions": [],
    "examples": [],
    "synonyms": [
      "casca",
      "pele",
      "crosta",
      "súber"
    ]
  },
  "casco": {
    "definitions": [],
    "examples": [],
    "synonyms": [
      "pata",
      "pezunho",
      "casco",
      "elmo",
      "capacete"
    ]
  },
  "caspa": {
    "definitions": [],
    "examples": [],
    "synonyms": [
      "caspa"
    ]
  },
  "casta": {
    "definitions": [],
    "examples": [],
    "synonyms": [
      "casto",
      "casta",
      "castas"
    ]
  },
  "casto": {
    "definitions": [],
    "examples": [],
    "synonyms": [
      "casto",
      "casta"
    ]
  },
  "catar": {
    "definitions": [
      "O Qatar (também escrito Catar, e mais raramente Quatar ou Katar) é um país da Península Arábica, que ocupa uma península do Golfo\n    Pérsico e algumas ilhas adjacentes. É rodeado por esta extensão marítima, excepto a sul, onde tem pequenas fronteiras terrestres com os Emiratos\n    Árabes Unidos e com a Arábia Saudita. Tem fronteiras marítimas com o Irão, a norte, o com o Bahrein, a oeste. A sua capital é\n    Doha.",
      "procurar e recolher"
    ],
    "examples": [
      "apanhar cogumelos",
      "colher flores"
    ],
    "synonyms": [
      "catar",
      "qatar",
      "pescar",
      "apanhar",
      "colher"
    ]
  },
  "cauda": {
    "definitions": [],
    "examples": [],
    "synonyms": [
      "cauda",
      "rabo",
      "traseiro"
    ]
  },
  "caule": {
    "definitions": [],
    "examples": [],
    "synonyms": [
      "caule",
      "tronco"
    ]
  },
  "causa": {
    "definitions": [
      "uma série de ações avançando um princípio ou tendendo para um fim particular"
    ],
    "examples": [],
    "synonyms": [
      "causa",
      "processo",
      "pleito",
      "campanha",
      "conta",
      "motivo",
      "razão"
    ]
  },
  "cauto": {
    "definitions": [],
    "examples": [],
    "synonyms": [
      "cauto",
      "cauteloso",
      "prudente",
      "atento"
    ]
  },
  "cavar": {
    "definitions": [
      "fazer um buraco, especialmente com uma ferramenta manual",
      "soltar ou remover terra"
    ],
    "examples": [
      "não perfure aqui, há um cano de gás",
      "furar a parede",
      "perfure para o óleo",
      "os cupins furam buracos na parede",
      "nós devemos cavar",
      "cave a terra para aeração"
    ],
    "synonyms": [
      "cavar",
      "perfurar",
      "furar",
      "escavar"
    ]
  },
  "cavia": {
    "definitions": [],
    "examples": [],
    "synonyms": [
      "cavia"
    ]
  },
  "caçar": {
    "definitions": [
      "ir atrás com a intenção de pegar"
    ],
    "examples": [],
    "synonyms": [
      "caçar",
      "perseguir",
      "seguir"
    ]
  },
  "cação": {
    "definitions": [],
    "examples": [],
    "synonyms": [
      "cação"
    ]
  },
  "cdrom": {
    "definitions": [],
    "examples": [],
    "synonyms": [
      "cdrom"
    ]
  },
  "cebus": {
    "definitions": [],
    "examples": [],
    "synonyms": [
      "cebus"
    ]
  },
  "cecal": {
    "definitions": [],
    "examples": [],
    "synonyms": [
      "cecal"
    ]
  },
  "ceder": {
    "definitions": [
      "ser flexível sob estresse de força física",
      "Entregar-se",
      "render-se ou renunciar seu controle físico a outro"
    ],
    "examples": [],
    "synonyms": [
      "passar",
      "entregar",
      "ceder",
      "dar",
      "consentir",
      "sucumbir",
      "desistir",
      "conceder"
    ]
  },
  "cedro": {
    "definitions": [],
    "examples": [],
    "synonyms": [
      "cedro"
    ]
  },
  "cefeu": {
    "definitions": [],
    "examples": [],
    "synonyms": [
      "cefeu"
    ]
  },
  "cegar": {
    "definitions": [],
    "examples": [],
    "synonyms": [
      "cegar",
      "encandear"
    ]
  },
  "ceiba": {
    "definitions": [],
    "examples": [],
    "synonyms": [
      "ceiba"
    ]
  },
  "celha": {
    "definitions": [],
    "examples": [],
    "synonyms": [
      "celha",
      "cílio",
      "pestana"
    ]
  },
  "celta": {
    "definitions": [
      "Línguas celtas descendem do proto-celta, ou , um ramo da superfamília das línguas indo-europeias. O termo  foi\n    usado para descrever esse grupo de línguas por Edward Lhuyd em 1707, tendo sido usado muito antes por escritores gregos e romanos para descrever\n    algumas tribos da Gália central e da península Ibérica. Durante o primeiro milênio a.C., essas línguas eram faladas na Europa, do Golfo da\n    Biscaia e do Mar do Norte, na região do Reno e do Danúbio até o Mar Negro e a Península Balcânica Superior, chegando até a Ásia Menor (Galácia).\n    Atualmente, as línguas celtas estão limitadas a algumas áreas na Grã-Bretanha, Ilha de Man, Irlanda, Ilha Cape Breton, Patagônia e na península\n    da Bretanha na França. A difusão para a Ilha Cape Breton e a Patagônia ocorreu nos tempos modernos. Em todas essas áreas, as línguas celtas são\n    faladas agora apenas por minorias."
    ],
    "examples": [
      "celta comum",
      "celta"
    ],
    "synonyms": [
      "celta",
      "celtas",
      "céltico",
      "gaélica",
      "gaélico",
      "céltica"
    ]
  },
  "cenho": {
    "definitions": [],
    "examples": [],
    "synonyms": [
      "cenho"
    ]
  },
  "censo": {
    "definitions": [
      "uma contagem periódica da população"
    ],
    "examples": [],
    "synonyms": [
      "censo",
      "recenseamento"
    ]
  },
  "cerca": {
    "definitions": [],
    "examples": [],
    "synonyms": [
      "barreira",
      "paliçada",
      "cerca",
      "estacada",
      "aproximadamente"
    ]
  },
  "cerco": {
    "definitions": [],
    "examples": [],
    "synonyms": [
      "assédio",
      "cerco",
      "sítio"
    ]
  },
  "cerda": {
    "definitions": [],
    "examples": [],
    "synonyms": [
      "cerda"
    ]
  },
  "ceres": {
    "definitions": [],
    "examples": [],
    "synonyms": [
      "ceres"
    ]
  },
  "cerio": {
    "definitions": [],
    "examples": [],
    "synonyms": [
      "cerio",
      "cério"
    ]
  },
  "cerne": {
    "definitions": [],
    "examples": [],
    "synonyms": [
      "cerne",
      "substância",
      "essência",
      "centro"
    ]
  },
  "certo": {
    "definitions": [],
    "examples": [],
    "synonyms": [
      "preciso",
      "certo",
      "exato",
      "correcto",
      "inevitável",
      "seguro",
      "correto",
      "justo",
      "perfeito",
      "afinado",
      "exacto"
    ]
  },
  "cervo": {
    "definitions": [],
    "examples": [],
    "synonyms": [
      "veado",
      "veados",
      "cervo",
      "cervos",
      "cervidae",
      "cervídeos"
    ]
  },
  "cesta": {
    "definitions": [],
    "examples": [],
    "synonyms": [
      "cesto",
      "engradado",
      "cesta"
    ]
  },
  "cesto": {
    "definitions": [],
    "examples": [],
    "synonyms": [
      "balaio",
      "cesto",
      "engradado",
      "cesta"
    ]
  },
  "cetim": {
    "definitions": [],
    "examples": [],
    "synonyms": [
      "cetim"
    ]
  },
  "cetro": {
    "definitions": [],
    "examples": [],
    "synonyms": [
      "ceptro",
      "cetro"
    ]
  },
  "cetus": {
    "definitions": [],
    "examples": [],
    "synonyms": [
      "cetus"
    ]
  },
  "cevar": {
    "definitions": [
      "tornar gordo, aumentar de peso"
    ],
    "examples": [
      "Nós vamos engordar essa pobre criança morrendo de fome"
    ],
    "synonyms": [
      "engordar",
      "cevar"
    ]
  },
  "chade": {
    "definitions": [
      "O Chade, também chamado de Tchade ou Tchad (em árabe تشاد, transl. Tshād",
      "em francês: Tchad) é um país sem acesso ao mar,\n    localizado no centro-norte da África. Faz fronteira com a Líbia a norte, com o Sudão a leste, com a República Centro-Africana a sul, com Camarões\n    e Nigéria a sudoeste e com o Níger a oeste. Devido a sua distância do mar e seu clima predominantemente desértico, o país é por vezes referido\n    como o . O Chade é dividido em três regiões geográficas: a zona desértica no norte, um zona de Sahel no centro e uma\n    área de savana mais fértil no sul. O lago Chade, que deu nome à nação, é uma das regiões mais úmidas do continente africano. O monte mais alto do\n    Chade é o Emi Koussi, no Saara, e a maior cidade é a capital, N'Djamena. O país abriga mais de duzentos grupos étnicos e lingüísticos. O francês\n    e o árabe são as línguas oficiais e o islã é a religião mais praticada."
    ],
    "examples": [
      "coração morto da África"
    ],
    "synonyms": [
      "chade"
    ]
  },
  "chaga": {
    "definitions": [],
    "examples": [],
    "synonyms": [
      "úlcera",
      "chaga"
    ]
  },
  "chale": {
    "definitions": [],
    "examples": [],
    "synonyms": [
      "xaile",
      "xale",
      "chale"
    ]
  },
  "chalé": {
    "definitions": [],
    "examples": [],
    "synonyms": [
      "chalé",
      "casinhola",
      "casinha",
      "bangalô"
    ]
  },
  "chama": {
    "definitions": [],
    "examples": [],
    "synonyms": [
      "labareda",
      "fogo",
      "flama",
      "chama"
    ]
  },
  "chana": {
    "definitions": [],
    "examples": [],
    "synonyms": [
      "anhara",
      "savana",
      "chana"
    ]
  },
  "chapa": {
    "definitions": [],
    "examples": [],
    "synonyms": [
      "chapa",
      "estêncil",
      "placa",
      "lousa",
      "laje"
    ]
  },
  "chato": {
    "definitions": [
      "sem vivacidade ou animação",
      "tão carente de interesse que chega a causar cansaço mental"
    ],
    "examples": [],
    "synonyms": [
      "chato",
      "monótono",
      "desinteressante",
      "maçante",
      "aborrecido",
      "enfadonho",
      "tedioso",
      "entediante",
      "fastidioso",
      "cansativo"
    ]
  },
  "chave": {
    "definitions": [],
    "examples": [],
    "synonyms": [
      "chave",
      "interruptor",
      "tecla"
    ]
  },
  "checo": {
    "definitions": [
      "Tcheco ou checo é uma língua falada principalmente na República Tcheca (Checa) e que forma parte, junto com o polonês, o eslovaco e\n    o sórbio, do subgrupo ocidental das línguas eslavas. As línguas tcheca e eslovaca são mutuamente inteligíveis. Nas duas províncias da Boêmia e\n    Morávia e na parte meridional da Silésia é falado por cerca de 9,5 milhões de pessoas. Há também comunidades isoladas nos países\n    vizinhos."
    ],
    "examples": [],
    "synonyms": [
      "checo",
      "tcheco"
    ]
  },
  "chefa": {
    "definitions": [],
    "examples": [],
    "synonyms": [
      "directoria",
      "chefa",
      "amante"
    ]
  },
  "chefe": {
    "definitions": [],
    "examples": [],
    "synonyms": [
      "chefe",
      "supervisor",
      "capataz",
      "líder",
      "mestre",
      "patrão",
      "responsável",
      "cabeça",
      "liderança"
    ]
  },
  "cheia": {
    "definitions": [],
    "examples": [],
    "synonyms": [
      "cheia",
      "temporal",
      "aluvião",
      "dilúvio",
      "enchente",
      "inundação",
      "repleto",
      "cheio",
      "satisfeito",
      "repleta"
    ]
  },
  "cheio": {
    "definitions": [],
    "examples": [],
    "synonyms": [
      "cheio",
      "lotado",
      "pleno",
      "repleto",
      "satisfeito",
      "cheia",
      "repleta"
    ]
  },
  "chiar": {
    "definitions": [
      "ferver de raiva ou ressentimento profundo"
    ],
    "examples": [],
    "synonyms": [
      "assobiar",
      "chiar"
    ]
  },
  "chile": {
    "definitions": [
      "Chile, oficialmente República do Chile (em espanhol: ), é um país da América do Sul que ocupa uma longa e estreita faixa costeira\n    encravada entre a cordilheira dos Andes e o oceano Pacífico. Faz fronteira ao norte com o Peru, a nordeste com a Bolívia, a leste com a Argentina\n    e a Passagem de Drake, a ponta mais meridional do país. É um dos dois únicos países da América do Sul que não tem uma fronteira comum com o\n    Brasil, além do Equador. O Pacífico forma toda a fronteira oeste do país, com um litoral que se estende por 6.435 quilômetros. O território\n    chileno se estende até o Oceano Pacífico, que inclui os territórios ultramarinos de Arquipélago Juan Fernández, Ilhas de Sala y Gómez, as Ilhas\n    Desventuradas e a Ilha de Páscoa, localizada na Polinésia. O Chile possui uma reivindicação de 1.250.000 quilômetros quadrados de território na\n    Antártida."
    ],
    "examples": [],
    "synonyms": [
      "chile"
    ]
  },
  "chili": {
    "definitions": [],
    "examples": [],
    "synonyms": [
      "piripiri",
      "chili",
      "pimento"
    ]
  },
  "china": {
    "definitions": [
      "A República Popular da China (RPC) (chinês simplificado:中华人民共和国, chinês tradicional:中华人民共和国",
      "pinyin: ), vulgarmente conhecida como\n    China, é o maior país da Ásia Oriental e o mais populoso do mundo, com mais de 1,3 bilhão de habitantes, aproximadamente um quinto da população\n    da Terra. É uma república socialista governada pelo Partido Comunista da China sob um sistema de partido único e tem jurisdição sobre 22\n    províncias, cinco regiões autônomas (Xinjiang, Mongólia Interior, Tibete, Ningxia e Guangxi), quatro municípios (Pequim, Tianjin, Xangai e\n    Chongqing) e duas Regiões Administrativas Especiais com grande autonomia (Hong Kong e Macau). A capital da República Popular da China é\n    Pequim."
    ],
    "examples": [],
    "synonyms": [
      "china"
    ]
  },
  "chita": {
    "definitions": [],
    "examples": [],
    "synonyms": [
      "guepardo",
      "chita"
    ]
  },
  "choco": {
    "definitions": [],
    "examples": [],
    "synonyms": [
      "choco"
    ]
  },
  "chope": {
    "definitions": [],
    "examples": [],
    "synonyms": [
      "chope"
    ]
  },
  "choro": {
    "definitions": [],
    "examples": [],
    "synonyms": [
      "choro",
      "pranto"
    ]
  },
  "choça": {
    "definitions": [],
    "examples": [],
    "synonyms": [
      "cabana",
      "choça",
      "casebre",
      "choupana",
      "barraco"
    ]
  },
  "chulo": {
    "definitions": [],
    "examples": [],
    "synonyms": [
      "safado",
      "proxeneta",
      "chulo",
      "proxenetismo",
      "cafetão"
    ]
  },
  "chupa": {
    "definitions": [],
    "examples": [],
    "synonyms": [
      "felação",
      "chupa"
    ]
  },
  "chute": {
    "definitions": [
      "palavras informais para qualquer tentativa ou esforço",
      "o ato de aplicar um golpe com o pé"
    ],
    "examples": [
      "ele deu um chute poderoso na bola"
    ],
    "synonyms": [
      "tacada",
      "chute",
      "pontapé"
    ]
  },
  "chuva": {
    "definitions": [],
    "examples": [],
    "synonyms": [
      "chuva"
    ]
  },
  "chuço": {
    "definitions": [],
    "examples": [],
    "synonyms": [
      "chuço",
      "lança",
      "pique"
    ]
  },
  "ciano": {
    "definitions": [],
    "examples": [],
    "synonyms": [
      "ciano",
      "turquesa"
    ]
  },
  "cicer": {
    "definitions": [],
    "examples": [],
    "synonyms": [
      "cicer"
    ]
  },
  "cicie": {
    "definitions": [],
    "examples": [],
    "synonyms": [
      "cicie",
      "sigmatismo"
    ]
  },
  "cicio": {
    "definitions": [],
    "examples": [],
    "synonyms": [
      "cicio",
      "burburinho",
      "sussurro",
      "murmúrio"
    ]
  },
  "ciclo": {
    "definitions": [
      "uma sequência de eventos repetida periodicamente"
    ],
    "examples": [],
    "synonyms": [
      "ciclo"
    ]
  },
  "cidra": {
    "definitions": [],
    "examples": [],
    "synonyms": [
      "cidra",
      "sidra",
      "cidreira"
    ]
  },
  "cifra": {
    "definitions": [
      "um método secreto da escrita"
    ],
    "examples": [],
    "synonyms": [
      "cifra",
      "número"
    ]
  },
  "cinco": {
    "definitions": [
      "sendo um mais de quatro"
    ],
    "examples": [],
    "synonyms": [
      "cinco",
      "v"
    ]
  },
  "cinta": {
    "definitions": [],
    "examples": [],
    "synonyms": [
      "cinta",
      "embrulhador",
      "banda"
    ]
  },
  "cinto": {
    "definitions": [],
    "examples": [],
    "synonyms": [
      "cinto"
    ]
  },
  "cinza": {
    "definitions": [],
    "examples": [],
    "synonyms": [
      "cinza",
      "cinzas",
      "cinzento",
      "gris",
      "cinzenta",
      "acinzentado"
    ]
  },
  "cioso": {
    "definitions": [],
    "examples": [],
    "synonyms": [
      "cioso",
      "ciumento"
    ]
  },
  "circe": {
    "definitions": [],
    "examples": [],
    "synonyms": [
      "circé",
      "circe"
    ]
  },
  "circo": {
    "definitions": [],
    "examples": [],
    "synonyms": [
      "circo"
    ]
  },
  "circé": {
    "definitions": [],
    "examples": [],
    "synonyms": [
      "circé",
      "circe"
    ]
  },
  "cirro": {
    "definitions": [],
    "examples": [],
    "synonyms": [
      "cirrus",
      "cirro"
    ]
  },
  "cisma": {
    "definitions": [],
    "examples": [],
    "synonyms": [
      "dissidência",
      "cisão",
      "cisma"
    ]
  },
  "cisne": {
    "definitions": [],
    "examples": [],
    "synonyms": [
      "cisne"
    ]
  },
  "cisto": {
    "definitions": [],
    "examples": [],
    "synonyms": [
      "furúnculo",
      "tumor",
      "bubão",
      "íngua",
      "cisto",
      "abcesso",
      "pústula",
      "carbúnculo",
      "quisto"
    ]
  },
  "cisão": {
    "definitions": [],
    "examples": [],
    "synonyms": [
      "dissidência",
      "cisão",
      "cisma"
    ]
  },
  "citar": {
    "definitions": [],
    "examples": [],
    "synonyms": [
      "mencionar",
      "citar",
      "aludir",
      "aduzir",
      "alegar"
    ]
  },
  "citas": {
    "definitions": [],
    "examples": [],
    "synonyms": [
      "citas"
    ]
  },
  "civil": {
    "definitions": [],
    "examples": [],
    "synonyms": [
      "civil",
      "civilizado"
    ]
  },
  "ciúme": {
    "definitions": [],
    "examples": [],
    "synonyms": [
      "ciúmes",
      "ciúme"
    ]
  },
  "clado": {
    "definitions": [],
    "examples": [],
    "synonyms": [
      "clado"
    ]
  },
  "clara": {
    "definitions": [],
    "examples": [],
    "synonyms": [
      "albumen",
      "albúmen",
      "clara"
    ]
  },
  "claro": {
    "definitions": [],
    "examples": [],
    "synonyms": [
      "claro",
      "brilhante",
      "luminoso",
      "vivído",
      "radiante",
      "naturalmente",
      "compreensivelmente",
      "decerto",
      "pálido",
      "rotundamente",
      "claramente"
    ]
  },
  "clava": {
    "definitions": [],
    "examples": [],
    "synonyms": [
      "porrete",
      "clava",
      "cacete"
    ]
  },
  "clave": {
    "definitions": [],
    "examples": [],
    "synonyms": [
      "clave"
    ]
  },
  "clero": {
    "definitions": [],
    "examples": [],
    "synonyms": [
      "clero"
    ]
  },
  "clima": {
    "definitions": [],
    "examples": [],
    "synonyms": [
      "vento",
      "tempo",
      "clima",
      "humor"
    ]
  },
  "clipe": {
    "definitions": [],
    "examples": [],
    "synonyms": [
      "clipe"
    ]
  },
  "clone": {
    "definitions": [],
    "examples": [],
    "synonyms": [
      "cover",
      "clone"
    ]
  },
  "cloro": {
    "definitions": [],
    "examples": [],
    "synonyms": [
      "cloro"
    ]
  },
  "cloto": {
    "definitions": [],
    "examples": [],
    "synonyms": [
      "cloto"
    ]
  },
  "clube": {
    "definitions": [],
    "examples": [],
    "synonyms": [
      "clube",
      "sociedade",
      "guilda",
      "ordem"
    ]
  },
  "coala": {
    "definitions": [],
    "examples": [],
    "synonyms": [
      "coala"
    ]
  },
  "cobol": {
    "definitions": [],
    "examples": [],
    "synonyms": [
      "cobol"
    ]
  },
  "cobra": {
    "definitions": [],
    "examples": [],
    "synonyms": [
      "vibora",
      "cobra",
      "víbora",
      "cobras",
      "ofídio",
      "serpente",
      "serpentes"
    ]
  },
  "cobre": {
    "definitions": [],
    "examples": [],
    "synonyms": [
      "moeda",
      "cobre",
      "dinheiro",
      "divisa"
    ]
  },
  "cocho": {
    "definitions": [],
    "examples": [],
    "synonyms": [
      "manjedoura",
      "cocho"
    ]
  },
  "codão": {
    "definitions": [],
    "examples": [],
    "synonyms": [
      "codão",
      "códon"
    ]
  },
  "coeso": {
    "definitions": [],
    "examples": [],
    "synonyms": [
      "coesivo",
      "coeso"
    ]
  },
  "cofre": {
    "definitions": [],
    "examples": [],
    "synonyms": [
      "cofre"
    ]
  },
  "coice": {
    "definitions": [],
    "examples": [],
    "synonyms": [
      "coice",
      "recuo"
    ]
  },
  "coifa": {
    "definitions": [],
    "examples": [],
    "synonyms": [
      "coifa"
    ]
  },
  "coima": {
    "definitions": [],
    "examples": [],
    "synonyms": [
      "multa",
      "coima",
      "fiança"
    ]
  },
  "coisa": {
    "definitions": [
      "uma ação"
    ],
    "examples": [
      "como voce pode fazer tal coisa?"
    ],
    "synonyms": [
      "coisa",
      "troço",
      "negócio",
      "coisas",
      "tralha"
    ]
  },
  "coito": {
    "definitions": [],
    "examples": [],
    "synonyms": [
      "coito",
      "cópula"
    ]
  },
  "colar": {
    "definitions": [
      "ficar ou estar em contacto estreito",
      "colar ou ficar junto e resistir a separação",
      "juntar ou prender com  cola",
      "fixar firmemente:",
      "fixar firmemente",
      "fixar com um material adesivo como cola"
    ],
    "examples": [
      "O vestido adere ao seu corpo",
      "A etiqueta colou na caixa",
      "Os grãos de arroz do sushi se aderem",
      "cole o sinal na parede",
      "corte e cole a frase no texto",
      "Será que este papel de parede se adere à parede?"
    ],
    "synonyms": [
      "aderir",
      "colar",
      "afixar",
      "cravar",
      "coleira",
      "grudar"
    ]
  },
  "colas": {
    "definitions": [],
    "examples": [],
    "synonyms": [
      "cola",
      "colas"
    ]
  },
  "colmo": {
    "definitions": [],
    "examples": [],
    "synonyms": [
      "palha",
      "colmo"
    ]
  },
  "colza": {
    "definitions": [],
    "examples": [],
    "synonyms": [
      "colza"
    ]
  },
  "comer": {
    "definitions": [
      "ter relações sexuais com alguém",
      "ter relações sexuais com",
      "preocupar ou causar ansiedade de uma forma persistente",
      "ingerir comida",
      "usado só por animais",
      "ingerir comida sólida",
      "comer uma refeição",
      "ter uma refeição",
      "tomar uma refeição"
    ],
    "examples": [
      "Esta aluna transa todos em seu dormitório",
      "Adão copulou Eva",
      "Você já foi foder com este homem?",
      "esse cachorro não se alimenta com certos tipos de carne",
      "oque as baleias comem?",
      "ela estava comendo uma banana",
      "oque você comeu de jantar noite passada",
      "Nós não comemos até dez horas porque haviam tantos telefonemas",
      "Eu não comi ainda, então eu aceito seu convite de bom grado"
    ],
    "synonyms": [
      "almoçar",
      "comer",
      "montar",
      "pinar",
      "meter",
      "foder",
      "trepar",
      "transar",
      "copular",
      "consumir",
      "devorar"
    ]
  },
  "comum": {
    "definitions": [],
    "examples": [],
    "synonyms": [
      "normal",
      "costumeiro",
      "comum",
      "rotineiro",
      "ordinário",
      "genérico",
      "habitual",
      "geral",
      "usual",
      "recíproco",
      "mútuo",
      "popular",
      "vulgar",
      "vernáculo"
    ]
  },
  "comun": {
    "definitions": [],
    "examples": [],
    "synonyms": [
      "batido",
      "comun",
      "banal",
      "vulgar",
      "gasto",
      "trivial"
    ]
  },
  "conas": {
    "definitions": [
      "Termos obscenos para órgãos genitais femininos"
    ],
    "examples": [],
    "synonyms": [
      "xana",
      "xavasca",
      "buceta",
      "rata",
      "xoxota",
      "conas",
      "boceta",
      "vagina"
    ]
  },
  "conde": {
    "definitions": [
      "um nobre (em vários países), tendo o rank igual a um Conde britânico"
    ],
    "examples": [],
    "synonyms": [
      "conde"
    ]
  },
  "conga": {
    "definitions": [],
    "examples": [],
    "synonyms": [
      "conga"
    ]
  },
  "congo": {
    "definitions": [],
    "examples": [],
    "synonyms": [
      "congo"
    ]
  },
  "conta": {
    "definitions": [
      "o número total contado"
    ],
    "examples": [],
    "synonyms": [
      "enumeração",
      "conta",
      "contagem",
      "grânulo",
      "miçanga",
      "contabilidade",
      "fatura",
      "facturas",
      "factura",
      "contas",
      "nota",
      "causa"
    ]
  },
  "conto": {
    "definitions": [],
    "examples": [],
    "synonyms": [
      "conto",
      "história",
      "mentira",
      "mentirinha",
      "novela",
      "estória",
      "narração"
    ]
  },
  "copal": {
    "definitions": [],
    "examples": [],
    "synonyms": [
      "copal"
    ]
  },
  "copas": {
    "definitions": [],
    "examples": [],
    "synonyms": [
      "copas"
    ]
  },
  "copra": {
    "definitions": [],
    "examples": [],
    "synonyms": [
      "copra"
    ]
  },
  "copta": {
    "definitions": [
      "a língua litúrgica da Igreja Ortodoxa Copta usado no Egito e na Etiópia",
      "escrita no alfabeto grego"
    ],
    "examples": [],
    "synonyms": [
      "copta",
      "cóptico",
      "coptas"
    ]
  },
  "coque": {
    "definitions": [],
    "examples": [],
    "synonyms": [
      "coque"
    ]
  },
  "coral": {
    "definitions": [],
    "examples": [],
    "synonyms": [
      "coral"
    ]
  },
  "corar": {
    "definitions": [
      "ficar vermelho, como se estivesse embaraçado ou com vergonha"
    ],
    "examples": [
      "a menina corou quando um rapaz assobiou quanda ela passou"
    ],
    "synonyms": [
      "alvejar",
      "corar",
      "branquear",
      "embranquecer",
      "avermelhar",
      "enrubescer",
      "ruborizar",
      "rosar"
    ]
  },
  "corda": {
    "definitions": [],
    "examples": [],
    "synonyms": [
      "corda",
      "toa",
      "linha",
      "fio"
    ]
  },
  "cores": {
    "definitions": [
      "uma bandeira que mostra a sua nacionalidade"
    ],
    "examples": [],
    "synonyms": [
      "cores"
    ]
  },
  "cormo": {
    "definitions": [],
    "examples": [],
    "synonyms": [
      "cormo"
    ]
  },
  "corno": {
    "definitions": [
      "uma das protuberâncias ósseas nas cabeças de certos ungulados"
    ],
    "examples": [],
    "synonyms": [
      "chifre",
      "galhada",
      "corno",
      "chifrudo",
      "cuckold"
    ]
  },
  "coroa": {
    "definitions": [
      "O verso de uma moeda, que não tem a representação da cabeça de uma pessoa"
    ],
    "examples": [],
    "synonyms": [
      "diadema",
      "coroa",
      "bruxa"
    ]
  },
  "coros": {
    "definitions": [],
    "examples": [],
    "synonyms": [
      "coros",
      "coro"
    ]
  },
  "corpo": {
    "definitions": [],
    "examples": [],
    "synonyms": [
      "corpo",
      "cadáver",
      "defunto",
      "enchido",
      "tronco",
      "torso",
      "morto",
      "carne",
      "anatomia"
    ]
  },
  "corso": {
    "definitions": [],
    "examples": [],
    "synonyms": [
      "corso",
      "córsico"
    ]
  },
  "corte": {
    "definitions": [
      "o ato de penetrar ou abrir algo com um instrumento afiado",
      "o ato de reduzir a quantidade ou o número",
      "a maneira pela qual alguma coisa se encaixa"
    ],
    "examples": [],
    "synonyms": [
      "corte",
      "cortes",
      "palácio",
      "cortamento",
      "caimento",
      "feitio",
      "tribunal"
    ]
  },
  "corvo": {
    "definitions": [],
    "examples": [],
    "synonyms": [
      "corvo"
    ]
  },
  "corça": {
    "definitions": [],
    "examples": [],
    "synonyms": [
      "corça",
      "veados",
      "corço"
    ]
  },
  "corço": {
    "definitions": [],
    "examples": [],
    "synonyms": [
      "corça",
      "veados",
      "corço"
    ]
  },
  "coser": {
    "definitions": [],
    "examples": [],
    "synonyms": [
      "coser",
      "confeccionar",
      "costurar"
    ]
  },
  "cosmo": {
    "definitions": [],
    "examples": [],
    "synonyms": [
      "cosmo",
      "cosmos",
      "universo",
      "natureza",
      "criação",
      "mundo"
    ]
  },
  "costa": {
    "definitions": [],
    "examples": [],
    "synonyms": [
      "costa",
      "litoral",
      "orla",
      "ribanceira",
      "margem",
      "praia",
      "encosta",
      "ladeira",
      "subida",
      "declives",
      "declive",
      "beira"
    ]
  },
  "cotar": {
    "definitions": [],
    "examples": [],
    "synonyms": [
      "avaliar",
      "valorizar",
      "cotar"
    ]
  },
  "coupé": {
    "definitions": [],
    "examples": [],
    "synonyms": [
      "cupê",
      "coupé"
    ]
  },
  "couro": {
    "definitions": [],
    "examples": [],
    "synonyms": [
      "pele",
      "couros",
      "couro"
    ]
  },
  "couve": {
    "definitions": [],
    "examples": [],
    "synonyms": [
      "repolho",
      "couve",
      "vegetal"
    ]
  },
  "coven": {
    "definitions": [],
    "examples": [],
    "synonyms": [
      "coven"
    ]
  },
  "cover": {
    "definitions": [],
    "examples": [],
    "synonyms": [
      "cover",
      "clone"
    ]
  },
  "covil": {
    "definitions": [],
    "examples": [],
    "synonyms": [
      "covil",
      "antro",
      "toca"
    ]
  },
  "coxim": {
    "definitions": [],
    "examples": [],
    "synonyms": [
      "travesseiro",
      "coxim",
      "almofada",
      "descanso"
    ]
  },
  "cozer": {
    "definitions": [],
    "examples": [],
    "synonyms": [
      "cozer",
      "assar",
      "fornear"
    ]
  },
  "coçar": {
    "definitions": [
      "cortar ou desgastar a superfície de algo"
    ],
    "examples": [],
    "synonyms": [
      "raspar",
      "rascar",
      "coçar"
    ]
  },
  "crack": {
    "definitions": [],
    "examples": [],
    "synonyms": [
      "crack"
    ]
  },
  "cravo": {
    "definitions": [],
    "examples": [],
    "synonyms": [
      "cravo",
      "craveiro"
    ]
  },
  "credo": {
    "definitions": [],
    "examples": [],
    "synonyms": [
      "evangelho",
      "credo"
    ]
  },
  "creek": {
    "definitions": [],
    "examples": [],
    "synonyms": [
      "creek"
    ]
  },
  "creme": {
    "definitions": [],
    "examples": [],
    "synonyms": [
      "creme",
      "nata"
    ]
  },
  "crepe": {
    "definitions": [],
    "examples": [],
    "synonyms": [
      "crepe"
    ]
  },
  "creso": {
    "definitions": [],
    "examples": [],
    "synonyms": [
      "creso"
    ]
  },
  "creta": {
    "definitions": [],
    "examples": [],
    "synonyms": [
      "creta"
    ]
  },
  "criar": {
    "definitions": [
      "a causa para prociar (animais)",
      "criar projetos",
      "cuidar de uma criança sem amamentar"
    ],
    "examples": [
      "ela reproduz cachorros"
    ],
    "synonyms": [
      "criar",
      "produzir",
      "fazer",
      "construir",
      "reproduzir",
      "instituir",
      "desenvolver",
      "causar",
      "realizar",
      "provocar",
      "arquitetar",
      "desenhar"
    ]
  },
  "crime": {
    "definitions": [
      "um crime sério (como assassinar ou incendiar)",
      "(direito penal) um acto punível por lei",
      "geralmente considerado um ato maligno"
    ],
    "examples": [],
    "synonyms": [
      "crimes",
      "crime",
      "ofensa"
    ]
  },
  "crina": {
    "definitions": [],
    "examples": [],
    "synonyms": [
      "juba",
      "crina"
    ]
  },
  "crise": {
    "definitions": [],
    "examples": [],
    "synonyms": [
      "crise",
      "paroxismo",
      "convulsão"
    ]
  },
  "crivo": {
    "definitions": [],
    "examples": [],
    "synonyms": [
      "peneira",
      "coador",
      "crivo"
    ]
  },
  "croco": {
    "definitions": [],
    "examples": [],
    "synonyms": [
      "açafrão",
      "croco"
    ]
  },
  "cromo": {
    "definitions": [],
    "examples": [],
    "synonyms": [
      "cromio",
      "cromo",
      "crómio",
      "crômio"
    ]
  },
  "cruel": {
    "definitions": [],
    "examples": [],
    "synonyms": [
      "cruel",
      "desalmado",
      "brutal",
      "bárbaro",
      "feroz"
    ]
  },
  "créos": {
    "definitions": [],
    "examples": [],
    "synonyms": [
      "créos"
    ]
  },
  "cubar": {
    "definitions": [],
    "examples": [],
    "synonyms": [
      "cubar"
    ]
  },
  "cueca": {
    "definitions": [],
    "examples": [],
    "synonyms": [
      "cueca"
    ]
  },
  "culex": {
    "definitions": [],
    "examples": [],
    "synonyms": [
      "culex"
    ]
  },
  "culpa": {
    "definitions": [
      "responsabilidade por uma má situação ou evento"
    ],
    "examples": [],
    "synonyms": [
      "culpa",
      "delinquência",
      "criminalidade"
    ]
  },
  "culto": {
    "definitions": [],
    "examples": [],
    "synonyms": [
      "culto",
      "iluminado"
    ]
  },
  "cunha": {
    "definitions": [],
    "examples": [],
    "synonyms": [
      "cunha"
    ]
  },
  "cupim": {
    "definitions": [],
    "examples": [],
    "synonyms": [
      "cupim",
      "térmite",
      "térmites",
      "cupins"
    ]
  },
  "cupom": {
    "definitions": [],
    "examples": [],
    "synonyms": [
      "cupom",
      "bilhete"
    ]
  },
  "curar": {
    "definitions": [
      "curar ou recuperar"
    ],
    "examples": [
      "minha perda quebrada está melhorando"
    ],
    "synonyms": [
      "sanar",
      "curar",
      "sarar",
      "remediar",
      "melhorar",
      "cicatrizar"
    ]
  },
  "curdo": {
    "definitions": [
      "O curdo (کوردی, Kurdî) é o nome do idioma indo-europeu falado pelos cerca de 25 milhões de curdos, povo que habita a região\n    histórica do Curdistão, área que inclui partes dos atuais Irã, Iraque, Síria e Turquia. O curdo pertence ao subgrupo noroeste das línguas\n    iranianas, que por sua vez pertencem ao ramo indo-iraniano da família linguística indo-européia. Os idiomas mais próximos do curdo são o balúchi,\n    o gilaki e o talysh, todos também pertencentes ao ramo noroeste das línguas iranianas. O persa também é aparentado ao curdo, embora pertença ao\n    ramo sudoeste destes idiomas."
    ],
    "examples": [],
    "synonyms": [
      "curdo"
    ]
  },
  "curie": {
    "definitions": [],
    "examples": [],
    "synonyms": [
      "curie"
    ]
  },
  "curro": {
    "definitions": [],
    "examples": [],
    "synonyms": [
      "curro"
    ]
  },
  "curry": {
    "definitions": [],
    "examples": [],
    "synonyms": [
      "curry",
      "caril"
    ]
  },
  "curso": {
    "definitions": [
      "curso de ação",
      "educação transmitida em uma série de aulas ou reuniões"
    ],
    "examples": [
      "se você persistir nesse caminho, irá certamente falhar",
      "uma vez que uma nação  embarca em uma conduta torna-se   extremamente difícil que alguma retração aconteça",
      "ele fez um curso de cestaria"
    ],
    "synonyms": [
      "conduta",
      "curso",
      "caminho",
      "corrente",
      "ano",
      "classe",
      "direcção",
      "direção",
      "rumo",
      "aula"
    ]
  },
  "curto": {
    "definitions": [
      "alguma coisa de pequena duração ou distância"
    ],
    "examples": [
      "uma breve estadia no país"
    ],
    "synonyms": [
      "curto",
      "lacônico",
      "breve"
    ]
  },
  "curva": {
    "definitions": [],
    "examples": [],
    "synonyms": [
      "curva",
      "curvas",
      "arco"
    ]
  },
  "curvo": {
    "definitions": [],
    "examples": [],
    "synonyms": [
      "tortuoso",
      "curvo",
      "circunflexo"
    ]
  },
  "cusco": {
    "definitions": [],
    "examples": [],
    "synonyms": [
      "cusco"
    ]
  },
  "cuspe": {
    "definitions": [],
    "examples": [],
    "synonyms": [
      "cuspe",
      "cuspo",
      "saliva"
    ]
  },
  "cuspo": {
    "definitions": [],
    "examples": [],
    "synonyms": [
      "cuspe",
      "cuspo",
      "saliva"
    ]
  },
  "custo": {
    "definitions": [],
    "examples": [],
    "synonyms": [
      "custo",
      "taxa",
      "remunerações",
      "estipêndio",
      "preço",
      "preços",
      "despesa",
      "custos",
      "gastos"
    ]
  },
  "cutia": {
    "definitions": [],
    "examples": [],
    "synonyms": [
      "cutia"
    ]
  },
  "cuzão": {
    "definitions": [],
    "examples": [],
    "synonyms": [
      "ânus",
      "pentelho",
      "rabo",
      "cuzão"
    ]
  },
  "cuíca": {
    "definitions": [],
    "examples": [],
    "synonyms": [
      "seringüê",
      "didelphimorphia",
      "timbu",
      "saragüéia",
      "gambá",
      "didelfo",
      "sarigueia",
      "didelphidae",
      "cuíca"
    ]
  },
  "cádis": {
    "definitions": [],
    "examples": [],
    "synonyms": [
      "cádis"
    ]
  },
  "cárie": {
    "definitions": [],
    "examples": [],
    "synonyms": [
      "cárie"
    ]
  },
  "cério": {
    "definitions": [],
    "examples": [],
    "synonyms": [
      "cerio",
      "cério"
    ]
  },
  "césar": {
    "definitions": [],
    "examples": [],
    "synonyms": [
      "césar"
    ]
  },
  "césio": {
    "definitions": [],
    "examples": [],
    "synonyms": [
      "césio"
    ]
  },
  "cílio": {
    "definitions": [],
    "examples": [],
    "synonyms": [
      "celha",
      "cílio",
      "pestana"
    ]
  },
  "cítia": {
    "definitions": [],
    "examples": [],
    "synonyms": [
      "cítia"
    ]
  },
  "códon": {
    "definitions": [],
    "examples": [],
    "synonyms": [
      "codão",
      "códon"
    ]
  },
  "cólon": {
    "definitions": [],
    "examples": [],
    "synonyms": [
      "cólon"
    ]
  },
  "cópia": {
    "definitions": [],
    "examples": [],
    "synonyms": [
      "cópia",
      "reprodução",
      "xerox",
      "fotocópia"
    ]
  },
  "cúrio": {
    "definitions": [],
    "examples": [],
    "synonyms": [
      "cúrio"
    ]
  },
  "cútis": {
    "definitions": [],
    "examples": [],
    "synonyms": [
      "cútis",
      "derme"
    ]
  }
}